{
  "context_id": "dc2aefd6-516c-4806-a7dd-10b4fd7de4a5",
  "context_type": "model",
  "created_at": "2025-09-20T17:05:38.325716",
  "updated_at": "2025-09-20T17:05:38.325716",
  "status": "active",
  "metadata": {},
  "content": {
    "collaboration": {
      "collaboration_id": "collab_20250920170538325716",
      "task_id": "task_001",
      "participating_agents": [
        "agent_001",
        "agent_002"
      ],
      "start_time": "2025-09-20T17:05:38.325716",
      "status": "active"
    }
  },
  "version": "1.0",
  "tags": []
}