{
  "context_id": "f938108e-11a3-44bd-afce-077eb6a34a19",
  "context_type": "memory",
  "created_at": "2025-09-23T18:09:07.206745",
  "updated_at": "2025-09-23T18:09:07.206745",
  "status": "active",
  "metadata": {},
  "content": {
    "memory_transfer": {
      "source_memory_id": "mem_20250923180906383356",
      "target_memory_id": "mem_20250923180907204730",
      "source_type": "short_term",
      "target_type": "long_term",
      "transfer_time": "2025-09-23T18:09:07.206745"
    }
  },
  "version": "1.0",
  "tags": []
}